Metadata-Version: 1.0
Name: Binomial-Gaussian-practice
Version: 1.0
Summary: Gaussian & Binomial distributions
Home-page: UNKNOWN
Author: Sandeep
Author-email: UNKNOWN
License: UNKNOWN
Platform: UNKNOWN
